{"cameraMode":{"drawMode":0,"name":"Shaded","section":"Shading Mode"},"sceneLighting":true,"audioPlay":false,"sceneViewState":{"showFog":true,"showMaterialUpdate":false,"showSkybox":true,"showFlares":true,"showImageEffects":true,"showParticleSystems":true},"in2DMode":false,"pivot":{"x":-12.74600887298584,"y":-4.073989391326904,"z":35.367977142333987},"rotation":{"x":-0.27610477805137637,"y":-0.4965430498123169,"z":0.17023302614688874,"w":-0.8052434325218201},"size":57.15768814086914,"orthographic":false}